django_payflow/__init__.py
django_payflow/forms.py
django_payflow/models.py
django_payflow-2.0.1.dist-info/WHEEL
django_payflow-2.0.1.dist-info/METADATA
django_payflow-2.0.1.dist-info/RECORD
